scan_manager/__init__.py
scan_manager/widgets.py
scan_manager/images/scanner.svg
scan_manager/images/stapler.svg
scan_manager/images/trash_can.svg
scan_manager-0.0.1.dist-info/DESCRIPTION.rst
scan_manager-0.0.1.dist-info/METADATA
scan_manager-0.0.1.dist-info/RECORD
scan_manager-0.0.1.dist-info/WHEEL
scan_manager-0.0.1.dist-info/entry_points.txt
scan_manager-0.0.1.dist-info/metadata.json
scan_manager-0.0.1.dist-info/top_level.txt
