Metadata-Version: 2.0
Name: scan-manager
Version: 0.0.1
Summary: GUI app for collating images produced by a document scanner
Home-page: https://github.com/timmartin/ScanManager
Author: Tim Martin
Author-email: tim@asymptotic.co.uk
License: MIT
Keywords: scanner
Platform: UNKNOWN
Classifier: Development Status :: 3 - Alpha
Classifier: Intended Audience :: End Users/Desktop
Classifier: Topic :: Office/Business
Classifier: License :: OSI Approved :: MIT License
Classifier: Programming Language :: Python :: 2
Classifier: Programming Language :: Python :: 2.7
Requires-Dist: PySide (~=1.2.4)
Requires-Dist: fpdf (~=1.7.2)
